chasis_asa_micorservices/__init__.py
chasis_asa_micorservices/logger.py
chasis_asa_microservices-0.3.1.dist-info/METADATA
chasis_asa_microservices-0.3.1.dist-info/WHEEL
chasis_asa_microservices-0.3.1.dist-info/top_level.txt
chasis_asa_microservices-0.3.1.dist-info/RECORD
